latch_sdk_config/__init__.py
latch_sdk_config/latch.py
latch_sdk_config/user.py
latch_sdk_config-0.0.3.dist-info/LICENSE
latch_sdk_config-0.0.3.dist-info/METADATA
latch_sdk_config-0.0.3.dist-info/WHEEL
latch_sdk_config-0.0.3.dist-info/top_level.txt
latch_sdk_config-0.0.3.dist-info/RECORD
